masterTestModule/__init__.py
masterTestModule/add.py
masterTestModule/subtract.py
masterTestModule/extras/__init__.py
masterTestModule/extras/divide.py
masterTestModule/extras/multiply.py
masterTestModule/extras/squareNumber.py
masterTestModule/extras/squareRoot.py
masterTestModule-0.0.1.dist-info/METADATA
masterTestModule-0.0.1.dist-info/WHEEL
masterTestModule-0.0.1.dist-info/top_level.txt
masterTestModule-0.0.1.dist-info/RECORD
