Metadata-Version: 2.1
Name: masterTestModule
Version: 0.0.1
Summary: My test package which is legendary
Home-page: UNKNOWN
Author: Mr. H.B.
Author-email: <han.kagan.b@gmail.com>
License: UNKNOWN
Keywords: python,first package
Platform: UNKNOWN
Classifier: Development Status :: 3 - Alpha
Classifier: Intended Audience :: Education
Classifier: Programming Language :: Python :: 2
Classifier: Programming Language :: Python :: 3
Classifier: Operating System :: MacOS :: MacOS X
Classifier: Operating System :: Microsoft :: Windows
